[{"id": 0, "contents": "2023版和即时生效版最大区别在哪?"}, {"id": 1, "contents": "是否所有的门急诊医疗保险金都可以赔付?"}, {"id": 2, "contents": "互联网问诊和购药费用如何使用?"}, {"id": 3, "contents": "健康检查及疫苗责任，就医的医院范围?"}, {"id": 4, "contents": "健康检查都包含什么,儿保服务次数和内容有哪些?"}, {"id": 5, "contents": "哪些项目不属于健康检查责任?"}, {"id": 6, "contents": "防控近视保障对镜片有什么要求吗?"}, {"id": 7, "contents": "去指定私立网络就诊，忘了出示直付保险卡，可不可以事后提供收据报销?"}, {"id": 8, "contents": "此产品保证续保吗?"}, {"id": 9, "contents": "此产有犹豫期退保嘛?"}, {"id": 10, "contents": "“京东安联成长优享”事先授权条款有写被保险人在接受治疗前要向贵司提前5个工作日申请但如果情况很紧急，被保险人需要马上住院或者急诊需要住院怎么办，可以先住院治疗再申请吗?"}, {"id": 11, "contents": "“京东安联成长优享”小海星计划中责任免除第四点第二条写到“本附加合同约定医疗机构外产生的医疗费用(持本附加合同约定医疗机构主治医生处方和院外购药原因说明的院外购药费用不在此限)”，第三方管理机构风石健康说这是不赔付的，请问这一条怎么解读呢。"}, {"id": 12, "contents": "京东安联成长优享2023”是否可以进行院外购药，责任免除没有查到相关描述，请问院外购药赔还是不赔?"}, {"id": 13, "contents": "“京东安联成长优享2023”健康检查及疫苗责任中约定需要选定一个医疗品牌就医，请问如果是前往公立医院接种疫苗，也只能去医疗网络中的其中一家吗?"}, {"id": 14, "contents": "京东安联成长优享2023”理赔时对住院病房有限制吗，比如只能标准单人间或者高档病房?"}, {"id": 15, "contents": "京东安联成长优2023-成长PLUS计划”住院及特定门诊医疗费用保险金责任中提到北京新世纪儿童医院/妇儿医院约定的20%住院自付比例，是需要自付总住院费用的20%还是需要扣除住院免赔额1万后再自付20%?"}, {"id": 16, "contents": "如等待期内罹患某项疾病投保时除外承保了但过了等待期再次患上相同疾病，该疾病会算成既往症不保障吗?"}, {"id": 17, "contents": "京东安联成长优享2023-家庭计划”中公立医院住院陪诊和垫付怎么使用，流程是什么样的呢?"}, {"id": 18, "contents": "投保时属于除外责任，但在后续检查中已痊愈的疾病，是否可以根据检查报告或者病例情况申请投保呢?"}, {"id": 19, "contents": "成长优享能报销儿童保健的费用吗?假如宝贝感冒发烧，从挂号开始，看诊、验血、开药都赔付吗?"}, {"id": 20, "contents": "首年出险后，第二年能续保么?"}, {"id": 21, "contents": "成长优享，已经确诊腺样体肥大的话，购买保险后过了等待期做腺样体手术是可以赔付的对吗?"}, {"id": 22, "contents": "成长优享”的门诊就诊前10次全部赔付，11次开始自付200元，那如果同一天挂了三个科室，是算一次还是三次?"}, {"id": 23, "contents": "如自己前往公立医院门诊就诊，但未向贵司申请理赔，是否不算一次门诊就诊?"}]